README.rst
setup.cfg
setup.py
eachpng/__init__.py
eachpng/eachpng.py
eachpng/version.py
eachpng.egg-info/PKG-INFO
eachpng.egg-info/SOURCES.txt
eachpng.egg-info/dependency_links.txt
eachpng.egg-info/entry_points.txt
eachpng.egg-info/requires.txt
eachpng.egg-info/top_level.txt