Metadata-Version: 1.1
Name: eachpng
Version: 0.0.2
Summary: Executes command line for each PNG from standard input and forwards their output to stdout.
Home-page: https://github.com/pebble/eachpng
Author: Pebble Technology
Author-email: UNKNOWN
License: MIT
Download-URL: https://github.com/pebble/eachpng/tarball/0.0.2
Platform: UNKNOWN
